{
  "table": [
    {
      "occured_at": "<a href='/Akomas/AkomasDetay.aspx?afet=79623'> FL-20201002-  -TUR</a>",
      "city": "Rize"
    },
    {
      "occured_at": "<a href='/Akomas/AkomasDetay.aspx?afet=79607'> FL-20200926- 0817 -TUR</a>",
      "city": "Bingöl"
    },
    {
      "occured_at": "<a href='/Akomas/AkomasDetay.aspx?afet=79536'> FL-20200822- 0733 -TUR</a>",
      "city": "Giresun"
    },
    {
      "occured_at": "<a href='/Akomas/AkomasDetay.aspx?afet=79477'> FL-20200802- 0673 -TUR</a>",
      "city": "Erzurum"
    },
    {
      "occured_at": "<a href='/Akomas/AkomasDetay.aspx?afet=79476'> FL-20200802- 0672 -TUR</a>",
      "city": "Ağrı"
    },
    {
      "occured_at": "<a href='/Akomas/AkomasDetay.aspx?afet=79432'> FL-20200713- 0628 -TUR</a>",
      "city": "Bitlis"
    },
    {
      "occured_at": "<a href='/Akomas/AkomasDetay.aspx?afet=79430'> FL-20200713- 0626 -TUR</a>",
      "city": "Erzurum"
    },
    {
      "occured_at": "<a href='/Akomas/AkomasDetay.aspx?afet=79431'> FL-20200713- 0627- TUR</a>",
      "city": "Rize"
    },
    {
      "occured_at": "<a href='/Akomas/AkomasDetay.aspx?afet=79417'> FL-20200712- 0614 -TUR</a>",
      "city": "Van"
    },
    {
      "occured_at": "<a href='/Akomas/AkomasDetay.aspx?afet=79416'> LS-202007012- 0613 -TUR</a>",
      "city": "Artvin"
    },
    {
      "occured_at": "<a href='/Akomas/AkomasDetay.aspx?afet=79415'> FL-20200711- 0612 -TUR</a>",
      "city": "Ağrı"
    },
    {
      "occured_at": "<a href='/Akomas/AkomasDetay.aspx?afet=79413'> FL-20200710- 0610 -TUR</a>",
      "city": "Kars"
    },
    {
      "occured_at": "<a href='/Akomas/AkomasDetay.aspx?afet=79409'> FL-20200708- 0606 -TUR</a>",
      "city": "Sivas"
    },
    {
      "occured_at": "<a href='/Akomas/AkomasDetay.aspx?afet=79387'> FL-20200705- 0583 -TUR</a>",
      "city": "Hakkari"
    },
    {
      "occured_at": "<a href='/Akomas/AkomasDetay.aspx?afet=79384'> FL-20200704- 0580 -TUR</a>",
      "city": "Kars"
    },
    {
      "occured_at": "<a href='/Akomas/AkomasDetay.aspx?afet=79380'> FL-20200701- 0576 -TUR</a>",
      "city": "Muş"
    },
    {
      "occured_at": "<a href='/Akomas/AkomasDetay.aspx?afet=79378'> FL-20200701- 0574 -TUR</a>",
      "city": "Ağrı"
    },
    {
      "occured_at": "<a href='/Akomas/AkomasDetay.aspx?afet=79363'> FL-20200624- 0559 -TUR</a>",
      "city": "Samsun"
    },
    {
      "occured_at": "<a href='/Akomas/AkomasDetay.aspx?afet=79360'> FL-20200623- 0556 -TUR</a>",
      "city": "İstanbul"
    },
    {
      "occured_at": "<a href='/Akomas/AkomasDetay.aspx?afet=79346'> FL-20200621- 0543 -TUR</a>",
      "city": "Kırklareli"
    },
    {
      "occured_at": "<a href='/Akomas/AkomasDetay.aspx?afet=79345'> FL-20200621- 0542 -TUR</a>",
      "city": "Bursa"
    },
    {
      "occured_at": "<a href='/Akomas/AkomasDetay.aspx?afet=79343'> FL-20200621- 0540 -TUR</a>",
      "city": "Ordu"
    },
    {
      "occured_at": "<a href='/Akomas/AkomasDetay.aspx?afet=79344'> FL-20200621- 0541 -TUR</a>",
      "city": "Balıkesir"
    },
    {
      "occured_at": "<a href='/Akomas/AkomasDetay.aspx?afet=79342'> FL-20200619- 0538 -TUR</a>",
      "city": "Sakarya"
    },
    {
      "occured_at": "<a href='/Akomas/AkomasDetay.aspx?afet=79339'> FL-20200618- 0535 -TUR</a>",
      "city": "Artvin"
    },
    {
      "occured_at": "<a href='/Akomas/AkomasDetay.aspx?afet=79335'> FL-20200617- 0531 -TUR</a>",
      "city": "Bingöl"
    },
    {
      "occured_at": "<a href='/Akomas/AkomasDetay.aspx?afet=79337'> FL-20200617- 0533 -TUR</a>",
      "city": "Erzurum"
    },
    {
      "occured_at": "<a href='/Akomas/AkomasDetay.aspx?afet=79164'> FL-20200402-0358 -TUR</a>",
      "city": "Elazığ"
    },
    {
      "occured_at": "<a href='/Akomas/AkomasDetay.aspx?afet=79060'> FL-20200314- 0255 -TUR</a>",
      "city": "Kahramanmaraş"
    },
    {
      "occured_at": "<a href='/Akomas/AkomasDetay.aspx?afet=78812'> FL-20200106-0002-TUR</a>",
      "city": "Balıkesir"
    },
    {
      "occured_at": "<a href='/Akomas/AkomasDetay.aspx?afet=77818'> FL-20191105-1214-TUR</a>",
      "city": "Muğla"
    },
    {
      "occured_at": "<a href='/Akomas/AkomasDetay.aspx?afet=77712'> FL-20191020-1157-TUR</a>",
      "city": "Muş"
    },
    {
      "occured_at": "<a href='/Akomas/AkomasDetay.aspx?afet=77596'> FL-20190928-1072-TUR</a>",
      "city": "Artvin"
    },
    {
      "occured_at": "<a href='/Akomas/AkomasDetay.aspx?afet=77494'> FL-20190823-0909-TUR</a>",
      "city": "Samsun"
    },
    {
      "occured_at": "<a href='/Akomas/AkomasDetay.aspx?afet=77284'> FL-20190817-0878-TUR</a>",
      "city": "İstanbul"
    },
    {
      "occured_at": "<a href='/Akomas/AkomasDetay.aspx?afet=77283'> FL-20190817-0877-TUR</a>",
      "city": "Bilecik"
    },
    {
      "occured_at": "<a href='/Akomas/AkomasDetay.aspx?afet=76910'> FL-20190718-0698-TUR</a>",
      "city": "Zonguldak"
    },
    {
      "occured_at": "<a href='/Akomas/AkomasDetay.aspx?afet=76909'> FL-20190718-0697-TUR</a>",
      "city": "Sakarya"
    },
    {
      "occured_at": "<a href='/Akomas/AkomasDetay.aspx?afet=76908'> FL-20190718-0696-TUR</a>",
      "city": "Düzce"
    },
    {
      "occured_at": "<a href='/Akomas/AkomasDetay.aspx?afet=76865'> FL-20190709-0653-TUR</a>",
      "city": "Van"
    },
    {
      "occured_at": "<a href='/Akomas/AkomasDetay.aspx?afet=76769'> FL-20190705-0604-TUR</a>",
      "city": "Çankırı"
    },
    {
      "occured_at": "<a href='/Akomas/AkomasDetay.aspx?afet=76614'> FL-20190622-0537-TUR</a>",
      "city": "Samsun"
    },
    {
      "occured_at": "<a href='/Akomas/AkomasDetay.aspx?afet=76608'> FL-20190620-0531-TUR</a>",
      "city": "Zonguldak"
    },
    {
      "occured_at": "<a href='/Akomas/AkomasDetay.aspx?afet=76609'> FL-20190620-0532-TUR</a>",
      "city": "Afyon"
    },
    {
      "occured_at": "<a href='/Akomas/AkomasDetay.aspx?afet=76605'> FL-20190619-0528-TUR</a>",
      "city": "Kırşehir"
    },
    {
      "occured_at": "<a href='/Akomas/AkomasDetay.aspx?afet=76604'> FL-20190618-0527-TUR</a>",
      "city": "Osmaniye"
    },
    {
      "occured_at": "<a href='/Akomas/AkomasDetay.aspx?afet=76602'> FL-20190618-0525-TUR</a>",
      "city": "Aydın"
    },
    {
      "occured_at": "<a href='/Akomas/AkomasDetay.aspx?afet=76601'> FL-20190618-0524-TUR</a>",
      "city": "Trabzon"
    },
    {
      "occured_at": "<a href='/Akomas/AkomasDetay.aspx?afet=76597'> FL-20190617-0520-TUR</a>",
      "city": "Giresun"
    },
    {
      "occured_at": "<a href='/Akomas/AkomasDetay.aspx?afet=76574'> FL-20190610-0497-TUR</a>",
      "city": "Kırıkkale"
    },
    {
      "occured_at": "<a href='/Akomas/AkomasDetay.aspx?afet=76559'> FL-20190609-0484-TUR</a>",
      "city": "Ankara"
    },
    {
      "occured_at": "<a href='/Akomas/AkomasDetay.aspx?afet=76554'> FL-20190603-0479-TUR</a>",
      "city": "Ankara"
    },
    {
      "occured_at": "<a href='/Akomas/AkomasDetay.aspx?afet=76243'> VI-20190504-0403-TUR</a>",
      "city": "Bitlis"
    },
    {
      "occured_at": "<a href='/Akomas/AkomasDetay.aspx?afet=76240'> FL-20190503-0400-TUR -</a>",
      "city": "Muş"
    },
    {
      "occured_at": "<a href='/Akomas/AkomasDetay.aspx?afet=75487'> FL-20190125-0066-TUR</a>",
      "city": "Burdur"
    },
    {
      "occured_at": "<a href='/Akomas/AkomasDetay.aspx?afet=74902'> FL-20190119-0039-TUR</a>",
      "city": "Osmaniye"
    },
    {
      "occured_at": "<a href='/Akomas/AkomasDetay.aspx?afet=74882'> FL-20190113-0019-TUR</a>",
      "city": "Mersin"
    },
    {
      "occured_at": "<a href='/Akomas/AkomasDetay.aspx?afet=74879'> FL-20190111-0016-TUR</a>",
      "city": "İzmir"
    },
    {
      "occured_at": "<a href='/Akomas/AkomasDetay.aspx?afet=74880'> FL-20190111-0017-TUR</a>",
      "city": "Manisa"
    },
    {
      "occured_at": "<a href='/Akomas/AkomasDetay.aspx?afet=74878'> FL-20190111-0015-TUR</a>",
      "city": "Kırklareli"
    },
    {
      "occured_at": "<a href='/Akomas/AkomasDetay.aspx?afet=74877'> FL-20190109-0014-TUR</a>",
      "city": "Hatay"
    },
    {
      "occured_at": "<a href='/Akomas/AkomasDetay.aspx?afet=74487'> FL-20180804-0487-TUR</a>",
      "city": "Rize"
    },
    {
      "occured_at": "<a href='/Akomas/AkomasDetay.aspx?afet=74483'> FL-20180731-0483-TUR</a>",
      "city": "Afyon"
    },
    {
      "occured_at": "<a href='/Akomas/AkomasDetay.aspx?afet=74368'> FL-20180713-0370-TUR</a>",
      "city": "Ordu"
    },
    {
      "occured_at": "<a href='/Akomas/AkomasDetay.aspx?afet=74265'> FL-20180626-0294-TUR</a>",
      "city": "Kars"
    },
    {
      "occured_at": "<a href='/Akomas/AkomasDetay.aspx?afet=74225'> FL-20180612-0234-TUR</a>",
      "city": "Konya"
    },
    {
      "occured_at": "<a href='/Akomas/AkomasDetay.aspx?afet=74173'> FL-20180529-0185-TUR</a>",
      "city": "Ankara"
    },
    {
      "occured_at": "<a href='/Akomas/AkomasDetay.aspx?afet=72181'> FL-20120629-0597-TUR</a>",
      "city": "Kars"
    },
    {
      "occured_at": "<a href='/Akomas/AkomasDetay.aspx?afet=74139'> FL-20180521-0152-TUR</a>",
      "city": "Erzurum"
    },
    {
      "occured_at": "<a href='/Akomas/AkomasDetay.aspx?afet=75782'> FL-20170928-1099-TUR</a>",
      "city": "Rize"
    },
    {
      "occured_at": "<a href='/Akomas/AkomasDetay.aspx?afet=75626'> FL-20170830-1001-TUR</a>",
      "city": "Denizli"
    },
    {
      "occured_at": "<a href='/Akomas/AkomasDetay.aspx?afet=75357'> FL-20170727-0863-TUR</a>",
      "city": "Edirne"
    },
    {
      "occured_at": "<a href='/Akomas/AkomasDetay.aspx?afet=75319'> FL-20170719-0827-TUR</a>",
      "city": "Bursa"
    },
    {
      "occured_at": "<a href='/Akomas/AkomasDetay.aspx?afet=75317'> FL-20170718-0825-TUR</a>",
      "city": "İstanbul"
    },
    {
      "occured_at": "<a href='/Akomas/AkomasDetay.aspx?afet=75318'> FL-20170718-0826-TUR</a>",
      "city": "Balıkesir"
    },
    {
      "occured_at": "<a href='/Akomas/AkomasDetay.aspx?afet=75247'> FL-20170704-0755-TUR -</a>",
      "city": "Yalova"
    },
    {
      "occured_at": "<a href='/Akomas/AkomasDetay.aspx?afet=75191'> FL-20170620-0699-TUR</a>",
      "city": "Sakarya"
    },
    {
      "occured_at": "<a href='/Akomas/AkomasDetay.aspx?afet=75105'> FL-20170609-0646-TUR</a>",
      "city": "Bolu"
    },
    {
      "occured_at": "<a href='/Akomas/AkomasDetay.aspx?afet=72128'> FL-20170414-0426-TUR</a>",
      "city": "Bitlis"
    },
    {
      "occured_at": "<a href='/Akomas/AkomasDetay.aspx?afet=72126'> FL-20170413-0424-TUR</a>",
      "city": "Bingöl"
    },
    {
      "occured_at": "<a href='/Akomas/AkomasDetay.aspx?afet=71779'> FL-20170117-0080-TUR</a>",
      "city": "Manisa"
    },
    {
      "occured_at": "<a href='/Akomas/AkomasDetay.aspx?afet=71749'> FL-2010115-0049-TUR</a>",
      "city": "Çanakkale"
    },
    {
      "occured_at": "<a href='/Akomas/AkomasDetay.aspx?afet=71673'> FL-20161229-1534-TUR</a>",
      "city": "Mersin"
    },
    {
      "occured_at": "<a href='/Akomas/AkomasDetay.aspx?afet=71557'> FL-20161130-1418-TUR</a>",
      "city": "Balıkesir"
    },
    {
      "occured_at": "<a href='/Akomas/AkomasDetay.aspx?afet=71254'> FL-20160921-1115-TUR</a>",
      "city": "Giresun"
    },
    {
      "occured_at": "<a href='/Akomas/AkomasDetay.aspx?afet=71253'> FL-20160921-1114-TUR</a>",
      "city": "Trabzon"
    },
    {
      "occured_at": "<a href='/Akomas/AkomasDetay.aspx?afet=71185'> FL-20160902-1047-TUR</a>",
      "city": "Rize"
    },
    {
      "occured_at": "<a href='/Akomas/AkomasDetay.aspx?afet=71138'> FL-20160821-1000-TUR</a>",
      "city": "Antalya"
    },
    {
      "occured_at": "<a href='/Akomas/AkomasDetay.aspx?afet=71139'> FL-20160821-1001-TUR</a>",
      "city": "Manisa"
    },
    {
      "occured_at": "<a href='/Akomas/AkomasDetay.aspx?afet=71096'> FL-20160813-0959-TUR</a>",
      "city": "Kastamonu"
    },
    {
      "occured_at": "<a href='/Akomas/AkomasDetay.aspx?afet=71095'> FL-20160813-0958-TUR</a>",
      "city": "Bartın"
    },
    {
      "occured_at": "<a href='/Akomas/AkomasDetay.aspx?afet=71094'> FL-20160812-0957-TUR</a>",
      "city": "Zonguldak"
    },
    {
      "occured_at": "<a href='/Akomas/AkomasDetay.aspx?afet=71089'> FL-20160808-0952-TUR</a>",
      "city": "Erzurum"
    },
    {
      "occured_at": "<a href='/Akomas/AkomasDetay.aspx?afet=71055'> FL-20160804-0918-TUR</a>",
      "city": "Antalya"
    },
    {
      "occured_at": "<a href='/Akomas/AkomasDetay.aspx?afet=70976'> FL-20160711-0840-TUR</a>",
      "city": "Van"
    },
    {
      "occured_at": "<a href='/Akomas/AkomasDetay.aspx?afet=70952'> FL-20160707-0816-TUR</a>",
      "city": "Kayseri"
    },
    {
      "occured_at": "<a href='/Akomas/AkomasDetay.aspx?afet=70951'> FL-20160707-0815-TUR</a>",
      "city": "Artvin"
    },
    {
      "occured_at": "<a href='/Akomas/AkomasDetay.aspx?afet=70950'> FL-20160706-0814-TUR</a>",
      "city": "Ordu"
    },
    {
      "occured_at": "<a href='/Akomas/AkomasDetay.aspx?afet=70921'> FL-20160630-0785-TUR</a>",
      "city": "Ardahan"
    },
    {
      "occured_at": "<a href='/Akomas/AkomasDetay.aspx?afet=70917'> FL-20160628-0782-TUR</a>",
      "city": "Çorum"
    },
    {
      "occured_at": "<a href='/Akomas/AkomasDetay.aspx?afet=70780'> FL-20160609-0674-TUR</a>",
      "city": "Hatay"
    },
    {
      "occured_at": "<a href='/Akomas/AkomasDetay.aspx?afet=70609'> FL-20160518-0575-TUR</a>",
      "city": "Kütahya"
    },
    {
      "occured_at": "<a href='/Akomas/AkomasDetay.aspx?afet=70062'> FL-20160305-0272-TUR</a>",
      "city": "Muş"
    },
    {
      "occured_at": "<a href='/Akomas/AkomasDetay.aspx?afet=69832'> FL-20160202-0165-TUR</a>",
      "city": "Kastamonu"
    },
    {
      "occured_at": "<a href='/Akomas/AkomasDetay.aspx?afet=69830'> FL-20160202-0163-TUR</a>",
      "city": "Karabük"
    },
    {
      "occured_at": "<a href='/Akomas/AkomasDetay.aspx?afet=69833'> FL-20160202-0166-TUR</a>",
      "city": "Bartın"
    },
    {
      "occured_at": "<a href='/Akomas/AkomasDetay.aspx?afet=69719'> FL-20160120-0093-TUR</a>",
      "city": "Bursa"
    },
    {
      "occured_at": "<a href='/Akomas/AkomasDetay.aspx?afet=69720'> EP-20160120-0094-TUR</a>",
      "city": "Eskişehir"
    },
    {
      "occured_at": "<a href='/Akomas/AkomasDetay.aspx?afet=69716'> FL-20160119-0090-TUR</a>",
      "city": "Manisa"
    },
    {
      "occured_at": "<a href='/Akomas/AkomasDetay.aspx?afet=69620'> FL-20160107-0020-TUR</a>",
      "city": "Kütahya"
    },
    {
      "occured_at": "<a href='/Akomas/AkomasDetay.aspx?afet=69363'> FL-20151111-1362-TUR</a>",
      "city": "Artvin"
    },
    {
      "occured_at": "<a href='/Akomas/AkomasDetay.aspx?afet=69362'> FL-20151111-1361-TUR</a>",
      "city": "Rize"
    },
    {
      "occured_at": "<a href='/Akomas/AkomasDetay.aspx?afet=69313'> FL-20151028-1312-TUR</a>",
      "city": "Şırnak"
    },
    {
      "occured_at": "<a href='/Akomas/AkomasDetay.aspx?afet=69311'> FL-20151027-1310-TUR</a>",
      "city": "Siirt"
    },
    {
      "occured_at": "<a href='/Akomas/AkomasDetay.aspx?afet=69308'> FL-20151026-1307-TUR</a>",
      "city": "Diyarbakır"
    },
    {
      "occured_at": "<a href='/Akomas/AkomasDetay.aspx?afet=69283'> FL-20151021-1281-TUR</a>",
      "city": "Aydın"
    },
    {
      "occured_at": "<a href='/Akomas/AkomasDetay.aspx?afet=69236'> FL-20151007-1234-TUR</a>",
      "city": "Zonguldak"
    },
    {
      "occured_at": "<a href='/Akomas/AkomasDetay.aspx?afet=69207'> FL-20150930-1205-TUR</a>",
      "city": "Sakarya"
    },
    {
      "occured_at": "<a href='/Akomas/AkomasDetay.aspx?afet=69206'> FL-20150929-1204-TUR</a>",
      "city": "Bursa"
    },
    {
      "occured_at": "<a href='/Akomas/AkomasDetay.aspx?afet=69184'> FL-20150923-1182-TUR</a>",
      "city": "Muğla"
    },
    {
      "occured_at": "<a href='/Akomas/AkomasDetay.aspx?afet=69181'> FL-20150921-1179-TUR</a>",
      "city": "İzmir"
    },
    {
      "occured_at": "<a href='/Akomas/AkomasDetay.aspx?afet=69182'> FL-20150921-1180-TUR</a>",
      "city": "Adana"
    },
    {
      "occured_at": "<a href='/Akomas/AkomasDetay.aspx?afet=69157'> FL-20150920-1157-TUR</a>",
      "city": "Manisa"
    },
    {
      "occured_at": "<a href='/Akomas/AkomasDetay.aspx?afet=68512'> FL-20150825-1069-TUR</a>",
      "city": "Van"
    },
    {
      "occured_at": "<a href='/Akomas/AkomasDetay.aspx?afet=68515'> FL-20150824-1067-TUR</a>",
      "city": "Rize"
    },
    {
      "occured_at": "<a href='/Akomas/AkomasDetay.aspx?afet=68516'> FL-20150824-1068-TUR</a>",
      "city": "Artvin"
    },
    {
      "occured_at": "<a href='/Akomas/AkomasDetay.aspx?afet=68605'> FL-20150802-0968-TUR</a>",
      "city": "Samsun"
    },
    {
      "occured_at": "<a href='/Akomas/AkomasDetay.aspx?afet=68611'> FL-20150801-0967-TUR</a>",
      "city": "Antalya"
    },
    {
      "occured_at": "<a href='/Akomas/AkomasDetay.aspx?afet=68705'> FL-20150627-0800-TUR</a>",
      "city": "Manisa"
    },
    {
      "occured_at": "<a href='/Akomas/AkomasDetay.aspx?afet=68714'> FL-20150625-0799-TUR</a>",
      "city": "Kastamonu"
    },
    {
      "occured_at": "<a href='/Akomas/AkomasDetay.aspx?afet=68721'> FL-20150624-0796-TUR</a>",
      "city": "Kırıkkale"
    },
    {
      "occured_at": "<a href='/Akomas/AkomasDetay.aspx?afet=68729'> FL-20150623-0793-TUR</a>",
      "city": "İzmir"
    },
    {
      "occured_at": "<a href='/Akomas/AkomasDetay.aspx?afet=68730'> FL-20150623-0794-TUR</a>",
      "city": "Kocaeli"
    },
    {
      "occured_at": "<a href='/Akomas/AkomasDetay.aspx?afet=68731'> FL-20150623-0795-TUR</a>",
      "city": "Sakarya"
    },
    {
      "occured_at": "<a href='/Akomas/AkomasDetay.aspx?afet=68764'> FL-20150616-0759-TUR</a>",
      "city": "Balıkesir"
    },
    {
      "occured_at": "<a href='/Akomas/AkomasDetay.aspx?afet=68766'> FL-20150616-0761-TUR</a>",
      "city": "Bilecik"
    },
    {
      "occured_at": "<a href='/Akomas/AkomasDetay.aspx?afet=68771'> FL-20150613-0743-TUR</a>",
      "city": "Çankırı"
    },
    {
      "occured_at": "<a href='/Akomas/AkomasDetay.aspx?afet=68789'> FL-20150609-0736-TUR</a>",
      "city": "Çorum"
    },
    {
      "occured_at": "<a href='/Akomas/AkomasDetay.aspx?afet=68790'> FL-20150609-0737-TUR</a>",
      "city": "Manisa"
    },
    {
      "occured_at": "<a href='/Akomas/AkomasDetay.aspx?afet=68794'> FL-20150607-0715-TUR</a>",
      "city": "Bursa"
    },
    {
      "occured_at": "<a href='/Akomas/AkomasDetay.aspx?afet=68810'> FL-20150603-0705-TUR</a>",
      "city": "Kırıkkale"
    },
    {
      "occured_at": "<a href='/Akomas/AkomasDetay.aspx?afet=68857'> FL-20150525-0669-TUR</a>",
      "city": "Ankara"
    },
    {
      "occured_at": "<a href='/Akomas/AkomasDetay.aspx?afet=68874'> FL-20150520-0647-TUR</a>",
      "city": "İzmir"
    },
    {
      "occured_at": "<a href='/Akomas/AkomasDetay.aspx?afet=68887'> FL-20150517-0616-TUR</a>",
      "city": "Ardahan"
    },
    {
      "occured_at": "<a href='/Akomas/AkomasDetay.aspx?afet=68920'> FL-20150511-0606-TUR</a>",
      "city": "Adana"
    },
    {
      "occured_at": "<a href='/Akomas/AkomasDetay.aspx?afet=69076'> FL-20150408-0441-TUR</a>",
      "city": "Kütahya"
    },
    {
      "occured_at": "<a href='/Akomas/AkomasDetay.aspx?afet=69079'> FL-20150407-0434-TUR</a>",
      "city": "Denizli"
    },
    {
      "occured_at": "<a href='/Akomas/AkomasDetay.aspx?afet=69081'> FL-20150407-0436-TUR</a>",
      "city": "Bursa"
    },
    {
      "occured_at": "<a href='/Akomas/AkomasDetay.aspx?afet=78242'> FL-20150402-0406-TUR</a>",
      "city": "Aydın"
    },
    {
      "occured_at": "<a href='/Akomas/AkomasDetay.aspx?afet=78236'> FL-20150330-0400-TUR</a>",
      "city": "Adıyaman"
    },
    {
      "occured_at": "<a href='/Akomas/AkomasDetay.aspx?afet=78234'> FL-20150330-0398-TUR</a>",
      "city": "Muş"
    },
    {
      "occured_at": "<a href='/Akomas/AkomasDetay.aspx?afet=78235'> FL-20150330-0399-TUR</a>",
      "city": "Siirt"
    },
    {
      "occured_at": "<a href='/Akomas/AkomasDetay.aspx?afet=78188'> FL-20150329-0366-TUR</a>",
      "city": "Şanlıurfa"
    },
    {
      "occured_at": "<a href='/Akomas/AkomasDetay.aspx?afet=78202'> FL-20150328-0363-TUR</a>",
      "city": "Antalya"
    },
    {
      "occured_at": "<a href='/Akomas/AkomasDetay.aspx?afet=78199'> FL-20150328-0364-TUR</a>",
      "city": "Konya"
    },
    {
      "occured_at": "<a href='/Akomas/AkomasDetay.aspx?afet=78203'> FL-20150328-0362-TUR</a>",
      "city": "Denizli"
    },
    {
      "occured_at": "<a href='/Akomas/AkomasDetay.aspx?afet=78207'> FL-20150328-0360-TUR</a>",
      "city": "Muğla"
    },
    {
      "occured_at": "<a href='/Akomas/AkomasDetay.aspx?afet=78205'> FL-20150328-0361-TUR</a>",
      "city": "Afyon"
    },
    {
      "occured_at": "<a href='/Akomas/AkomasDetay.aspx?afet=78280'> FL-20150320-0325-TUR</a>",
      "city": "Edirne"
    },
    {
      "occured_at": "<a href='/Akomas/AkomasDetay.aspx?afet=78308'> FL-20150314-0295-TUR</a>",
      "city": "Muğla"
    },
    {
      "occured_at": "<a href='/Akomas/AkomasDetay.aspx?afet=70848'> FL-20150302-0265-TUR</a>",
      "city": "Hatay"
    },
    {
      "occured_at": "<a href='/Akomas/AkomasDetay.aspx?afet=63351'> FL-20150227-0237-TUR</a>",
      "city": "Bursa"
    },
    {
      "occured_at": "<a href='/Akomas/AkomasDetay.aspx?afet=63379'> FL-20150224-0230-TUR</a>",
      "city": "İzmir"
    },
    {
      "occured_at": "<a href='/Akomas/AkomasDetay.aspx?afet=63377'> FL-20150224-0232-TUR</a>",
      "city": "Muğla"
    },
    {
      "occured_at": "<a href='/Akomas/AkomasDetay.aspx?afet=63403'> FL-20150219-0206-TUR</a>",
      "city": "Hatay"
    },
    {
      "occured_at": "<a href='/Akomas/AkomasDetay.aspx?afet=63435'> FL-20150215-0173-TUR</a>",
      "city": "Hatay"
    },
    {
      "occured_at": "<a href='/Akomas/AkomasDetay.aspx?afet=63436'> FL-20150213-0172-TUR</a>",
      "city": "Kahramanmaraş"
    },
    {
      "occured_at": "<a href='/Akomas/AkomasDetay.aspx?afet=63470'> FL-20150202-0138-TUR</a>",
      "city": "Tekirdağ"
    },
    {
      "occured_at": "<a href='/Akomas/AkomasDetay.aspx?afet=63493'> FL-20150201-0115-TUR</a>",
      "city": "Edirne"
    },
    {
      "occured_at": "<a href='/Akomas/AkomasDetay.aspx?afet=63497'> FL-20150131-0293-TUR</a>",
      "city": "Kırklareli"
    },
    {
      "occured_at": "<a href='/Akomas/AkomasDetay.aspx?afet=70851'> FL-20150131-0111-TUR</a>",
      "city": "Kırıkkale"
    },
    {
      "occured_at": "<a href='/Akomas/AkomasDetay.aspx?afet=63501'> FL-20150130-0107-TUR</a>",
      "city": "Muğla"
    },
    {
      "occured_at": "<a href='/Akomas/AkomasDetay.aspx?afet=63507'> FL-20150126-0101-TUR</a>",
      "city": "Çanakkale"
    },
    {
      "occured_at": "<a href='/Akomas/AkomasDetay.aspx?afet=63558'> FL-20150114-0051-TUR</a>",
      "city": "Denizli"
    },
    {
      "occured_at": "<a href='/Akomas/AkomasDetay.aspx?afet=63561'> FL-20150113-0048-TUR</a>",
      "city": "Antalya"
    },
    {
      "occured_at": "<a href='/Akomas/AkomasDetay.aspx?afet=63560'> FL-20150113-0049-TUR</a>",
      "city": "Muğla"
    },
    {
      "occured_at": "<a href='/Akomas/AkomasDetay.aspx?afet=63591'> FL-20150106-0017-TUR</a>",
      "city": "Hatay"
    },
    {
      "occured_at": "<a href='/Akomas/AkomasDetay.aspx?afet=63608'> FL-20150101-0001-TUR</a>",
      "city": "Aydın"
    },
    {
      "occured_at": "<a href='/Akomas/AkomasDetay.aspx?afet=63631'> FL-20141231-0159-TUR</a>",
      "city": "Muğla"
    },
    {
      "occured_at": "<a href='/Akomas/AkomasDetay.aspx?afet=63630'> FL-20141231-0160-TUR</a>",
      "city": "Manisa"
    },
    {
      "occured_at": "<a href='/Akomas/AkomasDetay.aspx?afet=78757'> FL-20141231-1056-TUR</a>",
      "city": "Muğla"
    },
    {
      "occured_at": "<a href='/Akomas/AkomasDetay.aspx?afet=78756'> FL-20141231-1055-TUR</a>",
      "city": "Muğla"
    },
    {
      "occured_at": "<a href='/Akomas/AkomasDetay.aspx?afet=78701'> FL-20141208-1002-TUR</a>",
      "city": "Antalya"
    },
    {
      "occured_at": "<a href='/Akomas/AkomasDetay.aspx?afet=78680'> FL-20141204-0981-TUR</a>",
      "city": "Edirne"
    },
    {
      "occured_at": "<a href='/Akomas/AkomasDetay.aspx?afet=78654'> FL-20141124-0955-TUR</a>",
      "city": "Siirt"
    },
    {
      "occured_at": "<a href='/Akomas/AkomasDetay.aspx?afet=78624'> FL-20141122-0925-TUR</a>",
      "city": "Samsun"
    },
    {
      "occured_at": "<a href='/Akomas/AkomasDetay.aspx?afet=78582'> FL-20141027-0883-TUR</a>",
      "city": "Kocaeli"
    },
    {
      "occured_at": "<a href='/Akomas/AkomasDetay.aspx?afet=78571'> FL-20141025-0872-TUR</a>",
      "city": "Antalya"
    },
    {
      "occured_at": "<a href='/Akomas/AkomasDetay.aspx?afet=78569'> FL-20141024-0870-TUR</a>",
      "city": "İzmir"
    },
    {
      "occured_at": "<a href='/Akomas/AkomasDetay.aspx?afet=78496'> VI-20140929-0800-TUR</a>",
      "city": "Osmaniye"
    },
    {
      "occured_at": "<a href='/Akomas/AkomasDetay.aspx?afet=78479'> FL-20140927-0783-TUR</a>",
      "city": "Hatay"
    },
    {
      "occured_at": "<a href='/Akomas/AkomasDetay.aspx?afet=78476'> FL-20140925-0780-TUR</a>",
      "city": "Hatay"
    },
    {
      "occured_at": "<a href='/Akomas/AkomasDetay.aspx?afet=78452'> FL-20140917-0756-TUR</a>",
      "city": "Aydın"
    },
    {
      "occured_at": "<a href='/Akomas/AkomasDetay.aspx?afet=78451'> FL-20140916-0755-TUR</a>",
      "city": "Çorum"
    },
    {
      "occured_at": "<a href='/Akomas/AkomasDetay.aspx?afet=78434'> FL-20140914-0738-TUR</a>",
      "city": "Kütahya"
    },
    {
      "occured_at": "<a href='/Akomas/AkomasDetay.aspx?afet=78431'> FL-20140911-0735-TUR</a>",
      "city": "Afyon"
    },
    {
      "occured_at": "<a href='/Akomas/AkomasDetay.aspx?afet=78357'> FL-20140821-0671-TUR</a>",
      "city": "Kayseri"
    },
    {
      "occured_at": "<a href='/Akomas/AkomasDetay.aspx?afet=78337'> FL-20140813-0651-TUR</a>",
      "city": "Erzurum"
    },
    {
      "occured_at": "<a href='/Akomas/AkomasDetay.aspx?afet=78106'> FL-20140807-0631-TUR</a>",
      "city": "İzmir"
    },
    {
      "occured_at": "<a href='/Akomas/AkomasDetay.aspx?afet=78060'> FL-20140727-0585-TUR</a>",
      "city": "Kırşehir"
    },
    {
      "occured_at": "<a href='/Akomas/AkomasDetay.aspx?afet=78033'> FL-20140720-0558-TUR</a>",
      "city": "Muğla"
    },
    {
      "occured_at": "<a href='/Akomas/AkomasDetay.aspx?afet=77751'> FL-20140606-0445-TUR</a>",
      "city": "Sakarya"
    },
    {
      "occured_at": "<a href='/Akomas/AkomasDetay.aspx?afet=77750'> FL-20140606-0444-TUR</a>",
      "city": "Ankara"
    },
    {
      "occured_at": "<a href='/Akomas/AkomasDetay.aspx?afet=77748'> FL-20140606-0442-TUR</a>",
      "city": "Adana"
    },
    {
      "occured_at": "<a href='/Akomas/AkomasDetay.aspx?afet=77747'> FL-20140606-0441-TUR</a>",
      "city": "Zonguldak"
    },
    {
      "occured_at": "<a href='/Akomas/AkomasDetay.aspx?afet=77749'> FL-20140606-0443-TUR</a>",
      "city": "Bolu"
    },
    {
      "occured_at": "<a href='/Akomas/AkomasDetay.aspx?afet=77746'> FL-20140605-0440-TUR</a>",
      "city": "Denizli"
    },
    {
      "occured_at": "<a href='/Akomas/AkomasDetay.aspx?afet=77745'> FL-20140605-0439-TUR</a>",
      "city": "Bilecik"
    },
    {
      "occured_at": "<a href='/Akomas/AkomasDetay.aspx?afet=77744'> FL-20140604-0438-TUR</a>",
      "city": "Çankırı"
    },
    {
      "occured_at": "<a href='/Akomas/AkomasDetay.aspx?afet=77680'> FL-20140526-0412-TUR</a>",
      "city": "Çorum"
    },
    {
      "occured_at": "<a href='/Akomas/AkomasDetay.aspx?afet=77681'> FL-20140526-0413-TUR</a>",
      "city": "Erzurum"
    },
    {
      "occured_at": "<a href='/Akomas/AkomasDetay.aspx?afet=76744'> FL-20140309-0184-TUR</a>",
      "city": "Adıyaman"
    },
    {
      "occured_at": "<a href='/Akomas/AkomasDetay.aspx?afet=76310'> FL-20140102-0001-TUR</a>",
      "city": "Muğla"
    },
    {
      "occured_at": "<a href='/Akomas/AkomasDetay.aspx?afet=73795'> FL-20131125-0930-TUR</a>",
      "city": "İzmir"
    },
    {
      "occured_at": "<a href='/Akomas/AkomasDetay.aspx?afet=73682'> FL-20131018-0810-TUR</a>",
      "city": "Bartın"
    },
    {
      "occured_at": "<a href='/Akomas/AkomasDetay.aspx?afet=73676'> FL-20131017-0807-TUR</a>",
      "city": "Antalya"
    },
    {
      "occured_at": "<a href='/Akomas/AkomasDetay.aspx?afet=73405'> FL-20130808-0557-TUR</a>",
      "city": "Samsun"
    },
    {
      "occured_at": "<a href='/Akomas/AkomasDetay.aspx?afet=73270'> FL-20130628-0403-TUR</a>",
      "city": "Van"
    },
    {
      "occured_at": "<a href='/Akomas/AkomasDetay.aspx?afet=73243'> FL-20130618-0375-TUR</a>",
      "city": "Ordu"
    },
    {
      "occured_at": "<a href='/Akomas/AkomasDetay.aspx?afet=73179'> FL-20130531-0332-TUR</a>",
      "city": "Iğdır"
    },
    {
      "occured_at": "<a href='/Akomas/AkomasDetay.aspx?afet=73050'> FL-20130417-0201-TUR</a>",
      "city": "Amasya"
    },
    {
      "occured_at": "<a href='/Akomas/AkomasDetay.aspx?afet=72980'> FL-20130317-0134-TUR</a>",
      "city": "Gümüşhane"
    },
    {
      "occured_at": "<a href='/Akomas/AkomasDetay.aspx?afet=72925'> FL-20130212-0079-TUR</a>",
      "city": "Aydın"
    },
    {
      "occured_at": "<a href='/Akomas/AkomasDetay.aspx?afet=72912'> FL-20130210-0066-TUR</a>",
      "city": "Balıkesir"
    },
    {
      "occured_at": "<a href='/Akomas/AkomasDetay.aspx?afet=72857'> FL-20130111-0018-TUR</a>",
      "city": "Antalya"
    },
    {
      "occured_at": "<a href='/Akomas/AkomasDetay.aspx?afet=73662'> FL-20131001-0763-TUR</a>",
      "city": "Bartın"
    },
    {
      "occured_at": "<a href='/Akomas/AkomasDetay.aspx?afet=72821'> FL-20121230-1221-TUR</a>",
      "city": "Muğla"
    },
    {
      "occured_at": "<a href='/Akomas/AkomasDetay.aspx?afet=72757'> FL-20121206-1166-TUR</a>",
      "city": "Balıkesir"
    },
    {
      "occured_at": "<a href='/Akomas/AkomasDetay.aspx?afet=72743'> FL-20121203-1161-TUR</a>",
      "city": "Çanakkale"
    },
    {
      "occured_at": "<a href='/Akomas/AkomasDetay.aspx?afet=72701'> FL-20121202-1146-TUR</a>",
      "city": "Balıkesir"
    },
    {
      "occured_at": "<a href='/Akomas/AkomasDetay.aspx?afet=72629'> FL-20121024-1037-TUR</a>",
      "city": "Sakarya"
    },
    {
      "occured_at": "<a href='/Akomas/AkomasDetay.aspx?afet=72627'> FL-20121023-1035-TUR</a>",
      "city": "Kırklareli"
    },
    {
      "occured_at": "<a href='/Akomas/AkomasDetay.aspx?afet=72628'> FL-20121023-1036-TUR</a>",
      "city": "Tekirdağ"
    },
    {
      "occured_at": "<a href='/Akomas/AkomasDetay.aspx?afet=72625'> FL-20121022-1033-TUR</a>",
      "city": "Balıkesir"
    },
    {
      "occured_at": "<a href='/Akomas/AkomasDetay.aspx?afet=72593'> FL-20121009-1001-TUR</a>",
      "city": "Trabzon"
    },
    {
      "occured_at": "<a href='/Akomas/AkomasDetay.aspx?afet=72590'> FL-20121008-0998-TUR</a>",
      "city": "Giresun"
    },
    {
      "occured_at": "<a href='/Akomas/AkomasDetay.aspx?afet=72565'> FL-20121004-0973-TUR</a>",
      "city": "Ordu"
    },
    {
      "occured_at": "<a href='/Akomas/AkomasDetay.aspx?afet=72566'> FL-20121004-0974-TUR</a>",
      "city": "Uşak"
    },
    {
      "occured_at": "<a href='/Akomas/AkomasDetay.aspx?afet=72531'> FL-20120922-0932-TUR</a>",
      "city": "Artvin"
    },
    {
      "occured_at": "<a href='/Akomas/AkomasDetay.aspx?afet=72339'> FL-20120807-0745-TUR</a>",
      "city": "Malatya"
    },
    {
      "occured_at": "<a href='/Akomas/AkomasDetay.aspx?afet=72315'> FL-20120801-0721-TUR</a>",
      "city": "Van"
    },
    {
      "occured_at": "<a href='/Akomas/AkomasDetay.aspx?afet=72204'> FL-20120704-0629-TUR</a>",
      "city": "Samsun"
    },
    {
      "occured_at": "<a href='/Akomas/AkomasDetay.aspx?afet=72180'> FL-20120628-0596-TUR</a>",
      "city": "Hakkari"
    },
    {
      "occured_at": "<a href='/Akomas/AkomasDetay.aspx?afet=70746'> FL-20120624-0568-TUR</a>",
      "city": "Nevşehir"
    },
    {
      "occured_at": "<a href='/Akomas/AkomasDetay.aspx?afet=70678'> FL-20120613-0528-TUR</a>",
      "city": "Van"
    },
    {
      "occured_at": "<a href='/Akomas/AkomasDetay.aspx?afet=70530'> FL-20120528-0477-TUR</a>",
      "city": "Edirne"
    },
    {
      "occured_at": "<a href='/Akomas/AkomasDetay.aspx?afet=70435'> FL-20120519-0434-TUR</a>",
      "city": "Kocaeli"
    },
    {
      "occured_at": "<a href='/Akomas/AkomasDetay.aspx?afet=70378'> FL-20120507-0404-TUR</a>",
      "city": "Siirt"
    },
    {
      "occured_at": "<a href='/Akomas/AkomasDetay.aspx?afet=70273'> FL-20120504-0384-TUR</a>",
      "city": "Yozgat"
    },
    {
      "occured_at": "<a href='/Akomas/AkomasDetay.aspx?afet=70274'> FL-20120504-0385-TUR</a>",
      "city": "Konya"
    },
    {
      "occured_at": "<a href='/Akomas/AkomasDetay.aspx?afet=70244'> FL-20120424-0355-TUR</a>",
      "city": "Manisa"
    },
    {
      "occured_at": "<a href='/Akomas/AkomasDetay.aspx?afet=70150'> FL-20120413-0312-TUR</a>",
      "city": "Ağrı"
    },
    {
      "occured_at": "<a href='/Akomas/AkomasDetay.aspx?afet=70096'> FL-20120408-0288-TUR</a>",
      "city": "Kastamonu"
    },
    {
      "occured_at": "<a href='/Akomas/AkomasDetay.aspx?afet=70039'> FL-20120328-0260-TUR</a>",
      "city": "Eskişehir"
    },
    {
      "occured_at": "<a href='/Akomas/AkomasDetay.aspx?afet=69995'> FL-20120321-0241-TUR</a>",
      "city": "Kütahya"
    },
    {
      "occured_at": "<a href='/Akomas/AkomasDetay.aspx?afet=69663'> FL-20120129-0088-TUR</a>",
      "city": "Hatay"
    },
    {
      "occured_at": "<a href='/Akomas/AkomasDetay.aspx?afet=69658'> FL-20120125-0083-TUR</a>",
      "city": "Antalya"
    },
    {
      "occured_at": "<a href='/Akomas/AkomasDetay.aspx?afet=64947'> FL-20120116-0058-TUR</a>",
      "city": "Kahramanmaraş"
    },
    {
      "occured_at": "<a href='/Akomas/AkomasDetay.aspx?afet=64972'> FL-20120110-0033-TUR</a>",
      "city": "Muğla"
    },
    {
      "occured_at": "<a href='/Akomas/AkomasDetay.aspx?afet=64973'> FL-20120110-0032-TUR</a>",
      "city": "Antalya"
    },
    {
      "occured_at": "<a href='/Akomas/AkomasDetay.aspx?afet=64997'> FL-20120107-0008-TUR</a>",
      "city": "Aydın"
    },
    {
      "occured_at": "<a href='/Akomas/AkomasDetay.aspx?afet=65000'> FL-20120107-0005-TUR</a>",
      "city": "Muğla"
    },
    {
      "occured_at": "<a href='/Akomas/AkomasDetay.aspx?afet=64998'> FL-20120107-0007-TUR</a>",
      "city": "Denizli"
    },
    {
      "occured_at": "<a href='/Akomas/AkomasDetay.aspx?afet=63868'> FL-20111208-1057-TUR</a>",
      "city": "Adana"
    },
    {
      "occured_at": "<a href='/Akomas/AkomasDetay.aspx?afet=64013'> FL-20111011-0910-TUR</a>",
      "city": "Van"
    },
    {
      "occured_at": "<a href='/Akomas/AkomasDetay.aspx?afet=64015'> FL-20111010-0908-TUR</a>",
      "city": "Denizli"
    },
    {
      "occured_at": "<a href='/Akomas/AkomasDetay.aspx?afet=64016'> FL-20111010-0907-TUR</a>",
      "city": "Isparta"
    },
    {
      "occured_at": "<a href='/Akomas/AkomasDetay.aspx?afet=64027'> FL-20111009-0896-TUR</a>",
      "city": "Antalya"
    },
    {
      "occured_at": "<a href='/Akomas/AkomasDetay.aspx?afet=64030'> FL-20111008-0893-TUR</a>",
      "city": "Muğla"
    },
    {
      "occured_at": "<a href='/Akomas/AkomasDetay.aspx?afet=64081'> FL-20110921-0842-TUR</a>",
      "city": "Balıkesir"
    },
    {
      "occured_at": "<a href='/Akomas/AkomasDetay.aspx?afet=64076'> FL-20110924-0847-TUR</a>",
      "city": "Rize"
    },
    {
      "occured_at": "<a href='/Akomas/AkomasDetay.aspx?afet=64205'> FL-20110819-0718-TUR</a>",
      "city": "Ordu"
    },
    {
      "occured_at": "<a href='/Akomas/AkomasDetay.aspx?afet=64244'> FL-20110812-0679-TUR</a>",
      "city": "Çankırı"
    },
    {
      "occured_at": "<a href='/Akomas/AkomasDetay.aspx?afet=64328'> FL-20110723-0595-TUR</a>",
      "city": "Giresun"
    },
    {
      "occured_at": "<a href='/Akomas/AkomasDetay.aspx?afet=64362'> FL-20110717-0561-TUR</a>",
      "city": "Samsun"
    },
    {
      "occured_at": "<a href='/Akomas/AkomasDetay.aspx?afet=64363'> FL-20110716-0560-TUR</a>",
      "city": "Van"
    },
    {
      "occured_at": "<a href='/Akomas/AkomasDetay.aspx?afet=64412'> FL-20110702-0512-TUR</a>",
      "city": "Erzincan"
    },
    {
      "occured_at": "<a href='/Akomas/AkomasDetay.aspx?afet=64439'> FL-20110623-0485-TUR</a>",
      "city": "Ankara"
    },
    {
      "occured_at": "<a href='/Akomas/AkomasDetay.aspx?afet=64449'> FL-20110617-0475-TUR</a>",
      "city": "Kırıkkale"
    },
    {
      "occured_at": "<a href='/Akomas/AkomasDetay.aspx?afet=64453'> FL-20110616-0471-TUR</a>",
      "city": "Konya"
    },
    {
      "occured_at": "<a href='/Akomas/AkomasDetay.aspx?afet=64452'> FL-20110616-0472-TUR</a>",
      "city": "Aydın"
    },
    {
      "occured_at": "<a href='/Akomas/AkomasDetay.aspx?afet=64456'> FL-20110614-0468-TUR</a>",
      "city": "Eskişehir"
    },
    {
      "occured_at": "<a href='/Akomas/AkomasDetay.aspx?afet=64475'> FL-20110612-0449-TUR</a>",
      "city": "Çanakkale"
    },
    {
      "occured_at": "<a href='/Akomas/AkomasDetay.aspx?afet=64501'> FL-20110602-0423-TUR</a>",
      "city": "Kastamonu"
    },
    {
      "occured_at": "<a href='/Akomas/AkomasDetay.aspx?afet=64503'> FL-20110601-0421-TUR</a>",
      "city": "Kütahya"
    },
    {
      "occured_at": "<a href='/Akomas/AkomasDetay.aspx?afet=64502'> FL-20110601-0422-TUR</a>",
      "city": "Kastamonu"
    },
    {
      "occured_at": "<a href='/Akomas/AkomasDetay.aspx?afet=64579'> FL-20110502-0345-TUR</a>",
      "city": "Osmaniye"
    },
    {
      "occured_at": "<a href='/Akomas/AkomasDetay.aspx?afet=64578'> FL-20110502-0346-TUR</a>",
      "city": "Şanlıurfa"
    },
    {
      "occured_at": "<a href='/Akomas/AkomasDetay.aspx?afet=64580'> FL-20110502-0344-TUR</a>",
      "city": "Samsun"
    },
    {
      "occured_at": "<a href='/Akomas/AkomasDetay.aspx?afet=64598'> FL-20110430-0326-TUR</a>",
      "city": "Adana"
    },
    {
      "occured_at": "<a href='/Akomas/AkomasDetay.aspx?afet=64625'> FL-20110422-0299-TUR</a>",
      "city": "Hakkari"
    },
    {
      "occured_at": "<a href='/Akomas/AkomasDetay.aspx?afet=64648'> FL-20110412-0276-TUR</a>",
      "city": "Osmaniye"
    },
    {
      "occured_at": "<a href='/Akomas/AkomasDetay.aspx?afet=64651'> FL-20110411-0273-TUR</a>",
      "city": "Gaziantep"
    },
    {
      "occured_at": "<a href='/Akomas/AkomasDetay.aspx?afet=64649'> FL-20110411-0275-TUR</a>",
      "city": "Adana"
    },
    {
      "occured_at": "<a href='/Akomas/AkomasDetay.aspx?afet=64677'> FL-20110402-0247-TUR</a>",
      "city": "Antalya"
    },
    {
      "occured_at": "<a href='/Akomas/AkomasDetay.aspx?afet=64698'> FL-20110321-0226-TUR</a>",
      "city": "Sivas"
    },
    {
      "occured_at": "<a href='/Akomas/AkomasDetay.aspx?afet=64697'> FL-20110321-0227-TUR</a>",
      "city": "Malatya"
    },
    {
      "occured_at": "<a href='/Akomas/AkomasDetay.aspx?afet=64712'> FL-20110317-0212-TUR</a>",
      "city": "Çorum"
    },
    {
      "occured_at": "<a href='/Akomas/AkomasDetay.aspx?afet=64758'> FL-20110224-0166-TUR</a>",
      "city": "İzmir"
    },
    {
      "occured_at": "<a href='/Akomas/AkomasDetay.aspx?afet=64841'> FL-20110128-0083-TUR</a>",
      "city": "Muğla"
    },
    {
      "occured_at": "<a href='/Akomas/AkomasDetay.aspx?afet=65025'> FL-20101230-0903-TUR</a>",
      "city": "Antalya"
    },
    {
      "occured_at": "<a href='/Akomas/AkomasDetay.aspx?afet=65024'> FL-20101230-0904-TUR</a>",
      "city": "Edirne"
    },
    {
      "occured_at": "<a href='/Akomas/AkomasDetay.aspx?afet=65026'> FL-20101228-0902-TUR</a>",
      "city": "Tekirdağ"
    },
    {
      "occured_at": "<a href='/Akomas/AkomasDetay.aspx?afet=65059'> FL-20101217-0869-TUR</a>",
      "city": "Antalya"
    },
    {
      "occured_at": "<a href='/Akomas/AkomasDetay.aspx?afet=65062'> FL-20101214-0866-TUR</a>",
      "city": "Antalya"
    },
    {
      "occured_at": "<a href='/Akomas/AkomasDetay.aspx?afet=65061'> FL-20101214-0867-TUR</a>",
      "city": "Konya"
    },
    {
      "occured_at": "<a href='/Akomas/AkomasDetay.aspx?afet=65209'> FL-20101210-0850-TUR</a>",
      "city": "Antalya"
    },
    {
      "occured_at": "<a href='/Akomas/AkomasDetay.aspx?afet=65210'> FL-20101210-0849-TUR</a>",
      "city": "Aydın"
    },
    {
      "occured_at": "<a href='/Akomas/AkomasDetay.aspx?afet=65088'> FL-20101126-0823-TUR</a>",
      "city": "Tekirdağ"
    },
    {
      "occured_at": "<a href='/Akomas/AkomasDetay.aspx?afet=65090'> FL-20101126-0821-TUR</a>",
      "city": "Antalya"
    },
    {
      "occured_at": "<a href='/Akomas/AkomasDetay.aspx?afet=65092'> FL-20101125-0819-TUR</a>",
      "city": "Antalya"
    },
    {
      "occured_at": "<a href='/Akomas/AkomasDetay.aspx?afet=65160'> FL-20101029-0749-TUR</a>",
      "city": "Kayseri"
    },
    {
      "occured_at": "<a href='/Akomas/AkomasDetay.aspx?afet=65159'> FL-20101029-0750-TUR</a>",
      "city": "İstanbul"
    },
    {
      "occured_at": "<a href='/Akomas/AkomasDetay.aspx?afet=65163'> FL-20101029-0746-TUR</a>",
      "city": "Bursa"
    },
    {
      "occured_at": "<a href='/Akomas/AkomasDetay.aspx?afet=65161'> FL-20101029-0748-TUR</a>",
      "city": "Kocaeli"
    },
    {
      "occured_at": "<a href='/Akomas/AkomasDetay.aspx?afet=65165'> FL-20101028-0744-TUR</a>",
      "city": "Manisa"
    },
    {
      "occured_at": "<a href='/Akomas/AkomasDetay.aspx?afet=65164'> FL-20101028-0745-TUR</a>",
      "city": "İstanbul"
    },
    {
      "occured_at": "<a href='/Akomas/AkomasDetay.aspx?afet=65186'> FL-20101019-0723-TUR</a>",
      "city": "Aydın"
    },
    {
      "occured_at": "<a href='/Akomas/AkomasDetay.aspx?afet=65222'> FL-20101015-0705-TUR</a>",
      "city": "Kahramanmaraş"
    },
    {
      "occured_at": "<a href='/Akomas/AkomasDetay.aspx?afet=65223'> FL-20101015-0704-TUR</a>",
      "city": "Manisa"
    },
    {
      "occured_at": "<a href='/Akomas/AkomasDetay.aspx?afet=65189'> FL-20101014-0720-TUR</a>",
      "city": "Bursa"
    },
    {
      "occured_at": "<a href='/Akomas/AkomasDetay.aspx?afet=65191'> FL-20101012-0718-TUR</a>",
      "city": "Van"
    },
    {
      "occured_at": "<a href='/Akomas/AkomasDetay.aspx?afet=65346'> FL-20100826-0580-TUR</a>",
      "city": "Rize"
    },
    {
      "occured_at": "<a href='/Akomas/AkomasDetay.aspx?afet=65415'> FL-20100805-0512-TUR</a>",
      "city": "Kütahya"
    },
    {
      "occured_at": "<a href='/Akomas/AkomasDetay.aspx?afet=65441'> FL-20100726-0486-TUR</a>",
      "city": "Kars"
    },
    {
      "occured_at": "<a href='/Akomas/AkomasDetay.aspx?afet=65442'> FL-20100726-0485-TUR</a>",
      "city": "Ardahan"
    },
    {
      "occured_at": "<a href='/Akomas/AkomasDetay.aspx?afet=65458'> FL-20100721-0469-TUR</a>",
      "city": "Erzurum"
    },
    {
      "occured_at": "<a href='/Akomas/AkomasDetay.aspx?afet=65491'> FL-20100714-0436-TUR</a>",
      "city": "Ağrı"
    },
    {
      "occured_at": "<a href='/Akomas/AkomasDetay.aspx?afet=65517'> FL-20100630-0410-TUR</a>",
      "city": "İstanbul"
    },
    {
      "occured_at": "<a href='/Akomas/AkomasDetay.aspx?afet=65518'> FL-20100629-0409-TUR</a>",
      "city": "Tekirdağ"
    },
    {
      "occured_at": "<a href='/Akomas/AkomasDetay.aspx?afet=65519'> FL-20100628-0408-TUR</a>",
      "city": "İstanbul"
    },
    {
      "occured_at": "<a href='/Akomas/AkomasDetay.aspx?afet=65534'> FL-20100624-0393-TUR</a>",
      "city": "Kocaeli"
    },
    {
      "occured_at": "<a href='/Akomas/AkomasDetay.aspx?afet=65537'> FL-20100623-0390-TUR</a>",
      "city": "Manisa"
    },
    {
      "occured_at": "<a href='/Akomas/AkomasDetay.aspx?afet=65536'> FL-20100623-0391-TUR</a>",
      "city": "İstanbul"
    },
    {
      "occured_at": "<a href='/Akomas/AkomasDetay.aspx?afet=65538'> FL-20100622-0389-TUR</a>",
      "city": "Bursa"
    },
    {
      "occured_at": "<a href='/Akomas/AkomasDetay.aspx?afet=65550'> FL-20100619-0377-TUR</a>",
      "city": "Denizli"
    },
    {
      "occured_at": "<a href='/Akomas/AkomasDetay.aspx?afet=65557'> FL-20100617-0370-TUR</a>",
      "city": "Trabzon"
    },
    {
      "occured_at": "<a href='/Akomas/AkomasDetay.aspx?afet=65556'> FL-20100617-0371-TUR</a>",
      "city": "Kastamonu"
    },
    {
      "occured_at": "<a href='/Akomas/AkomasDetay.aspx?afet=65559'> FL-20100616-0368-TUR</a>",
      "city": "Erzurum"
    },
    {
      "occured_at": "<a href='/Akomas/AkomasDetay.aspx?afet=65583'> FL-20100611-0345-TUR</a>",
      "city": "Bolu"
    },
    {
      "occured_at": "<a href='/Akomas/AkomasDetay.aspx?afet=65582'> FL-20100611-0346-TUR</a>",
      "city": "Kırıkkale"
    },
    {
      "occured_at": "<a href='/Akomas/AkomasDetay.aspx?afet=65584'> FL-20100609-0344-TUR</a>",
      "city": "Konya"
    },
    {
      "occured_at": "<a href='/Akomas/AkomasDetay.aspx?afet=65587'> FL-20100609-0341-TUR</a>",
      "city": "Sakarya"
    },
    {
      "occured_at": "<a href='/Akomas/AkomasDetay.aspx?afet=65589'> FL-20100608-0339-TUR</a>",
      "city": "İstanbul"
    },
    {
      "occured_at": "<a href='/Akomas/AkomasDetay.aspx?afet=65590'> FL-20100608-0337-TUR</a>",
      "city": "Amasya"
    },
    {
      "occured_at": "<a href='/Akomas/AkomasDetay.aspx?afet=65622'> FL-20100528-0306-TUR</a>",
      "city": "Denizli"
    },
    {
      "occured_at": "<a href='/Akomas/AkomasDetay.aspx?afet=65620'> FL-20100528-0308-TUR</a>",
      "city": "Kilis"
    },
    {
      "occured_at": "<a href='/Akomas/AkomasDetay.aspx?afet=65628'> FL-20100524-0299-TUR</a>",
      "city": "Muş"
    },
    {
      "occured_at": "<a href='/Akomas/AkomasDetay.aspx?afet=65652'> FL-20100512-0276-TUR</a>",
      "city": "Ağrı"
    },
    {
      "occured_at": "<a href='/Akomas/AkomasDetay.aspx?afet=65668'> FL-20100507-0261-TUR</a>",
      "city": "Muş"
    },
    {
      "occured_at": "<a href='/Akomas/AkomasDetay.aspx?afet=65672'> FL-20100504-0257-TUR</a>",
      "city": "Ağrı"
    },
    {
      "occured_at": "<a href='/Akomas/AkomasDetay.aspx?afet=65674'> FL-20100503-0255-TUR</a>",
      "city": "Ağrı"
    },
    {
      "occured_at": "<a href='/Akomas/AkomasDetay.aspx?afet=65675'> FL-20100503-0254-TUR</a>",
      "city": "Muş"
    },
    {
      "occured_at": "<a href='/Akomas/AkomasDetay.aspx?afet=65683'> FL-20100430-0247-TUR</a>",
      "city": "Adana"
    },
    {
      "occured_at": "<a href='/Akomas/AkomasDetay.aspx?afet=65684'> FL-20100429-0246-TUR</a>",
      "city": "Denizli"
    },
    {
      "occured_at": "<a href='/Akomas/AkomasDetay.aspx?afet=65702'> FL-20100423-0227-TUR</a>",
      "city": "Ağrı"
    },
    {
      "occured_at": "<a href='/Akomas/AkomasDetay.aspx?afet=65759'> FL-20100316-0171-TUR</a>",
      "city": "Ardahan"
    },
    {
      "occured_at": "<a href='/Akomas/AkomasDetay.aspx?afet=65760'> FL-20100316-0170-TUR</a>",
      "city": "Artvin"
    },
    {
      "occured_at": "<a href='/Akomas/AkomasDetay.aspx?afet=65789'> FL-20100224-0141-TUR</a>",
      "city": "Balıkesir"
    },
    {
      "occured_at": "<a href='/Akomas/AkomasDetay.aspx?afet=65790'> FL-20100224-0140-TUR</a>",
      "city": "Çanakkale"
    },
    {
      "occured_at": "<a href='/Akomas/AkomasDetay.aspx?afet=65803'> FL-20100221-0127-TUR</a>",
      "city": "Uşak"
    },
    {
      "occured_at": "<a href='/Akomas/AkomasDetay.aspx?afet=65808'> FL-20100216-0122-TUR</a>",
      "city": "Edirne"
    },
    {
      "occured_at": "<a href='/Akomas/AkomasDetay.aspx?afet=65806'> FL-20100216-0124-TUR</a>",
      "city": "Muğla"
    },
    {
      "occured_at": "<a href='/Akomas/AkomasDetay.aspx?afet=65807'> FL-20100216-0123-TUR</a>",
      "city": "Kırklareli"
    },
    {
      "occured_at": "<a href='/Akomas/AkomasDetay.aspx?afet=65811'> FL-20100215-0119-TUR</a>",
      "city": "Edirne"
    },
    {
      "occured_at": "<a href='/Akomas/AkomasDetay.aspx?afet=65826'> FL-20100213-0103-TUR</a>",
      "city": "İzmir"
    },
    {
      "occured_at": "<a href='/Akomas/AkomasDetay.aspx?afet=65825'> FL-20100213-0104-TUR</a>",
      "city": "Tekirdağ"
    },
    {
      "occured_at": "<a href='/Akomas/AkomasDetay.aspx?afet=65835'> FL-20100209-0094-TUR</a>",
      "city": "Antalya"
    },
    {
      "occured_at": "<a href='/Akomas/AkomasDetay.aspx?afet=65827'> FL-20100209-0102-TUR</a>",
      "city": "Edirne"
    },
    {
      "occured_at": "<a href='/Akomas/AkomasDetay.aspx?afet=65840'> FL-20100208-0089-TUR</a>",
      "city": "Muğla"
    },
    {
      "occured_at": "<a href='/Akomas/AkomasDetay.aspx?afet=65837'> FL-20100208-0092-TUR</a>",
      "city": "Antalya"
    },
    {
      "occured_at": "<a href='/Akomas/AkomasDetay.aspx?afet=65849'> FL-20100207-0081-TUR</a>",
      "city": "İzmir"
    },
    {
      "occured_at": "<a href='/Akomas/AkomasDetay.aspx?afet=65853'> FL-20100203-0077-TUR</a>",
      "city": "Manisa"
    },
    {
      "occured_at": "<a href='/Akomas/AkomasDetay.aspx?afet=65859'> FL-20100201-0071-TUR</a>",
      "city": "Kırklareli"
    },
    {
      "occured_at": "<a href='/Akomas/AkomasDetay.aspx?afet=65870'> FL-20100129-0060-TUR</a>",
      "city": "Antalya"
    },
    {
      "occured_at": "<a href='/Akomas/AkomasDetay.aspx?afet=65889'> FL-20100123-0041-TUR</a>",
      "city": "Muğla"
    },
    {
      "occured_at": "<a href='/Akomas/AkomasDetay.aspx?afet=65892'> FL-20100122-0038-TUR</a>",
      "city": "Muğla"
    },
    {
      "occured_at": "<a href='/Akomas/AkomasDetay.aspx?afet=66100'> FL-20091229-1279-TUR</a>",
      "city": "Antalya"
    },
    {
      "occured_at": "<a href='/Akomas/AkomasDetay.aspx?afet=66264'> FL-20091219-1256-TUR</a>",
      "city": "Muğla"
    },
    {
      "occured_at": "<a href='/Akomas/AkomasDetay.aspx?afet=66265'> FL-20091219-1255-TUR</a>",
      "city": "Hatay"
    },
    {
      "occured_at": "<a href='/Akomas/AkomasDetay.aspx?afet=66266'> FL-20091219-1254-TUR</a>",
      "city": "Hatay"
    },
    {
      "occured_at": "<a href='/Akomas/AkomasDetay.aspx?afet=66251'> FL-20091219-1267-TUR</a>",
      "city": "Hatay"
    },
    {
      "occured_at": "<a href='/Akomas/AkomasDetay.aspx?afet=66267'> FL-20091218-1253-TUR</a>",
      "city": ""
    },
    {
      "occured_at": "<a href='/Akomas/AkomasDetay.aspx?afet=66270'> FL-20091218-1250-TUR</a>",
      "city": "Muğla"
    },
    {
      "occured_at": "<a href='/Akomas/AkomasDetay.aspx?afet=66268'> FL-20091218-1252-TUR</a>",
      "city": "Antalya"
    },
    {
      "occured_at": "<a href='/Akomas/AkomasDetay.aspx?afet=66274'> FL-20091216-1246-TUR</a>",
      "city": "Antalya"
    },
    {
      "occured_at": "<a href='/Akomas/AkomasDetay.aspx?afet=66273'> FL-20091216-1247-TUR</a>",
      "city": "Muğla"
    },
    {
      "occured_at": "<a href='/Akomas/AkomasDetay.aspx?afet=66275'> FL-20091216-1245-TUR</a>",
      "city": "İzmir"
    },
    {
      "occured_at": "<a href='/Akomas/AkomasDetay.aspx?afet=66378'> FL-20091213-1232-TUR</a>",
      "city": "Yalova"
    },
    {
      "occured_at": "<a href='/Akomas/AkomasDetay.aspx?afet=66377'> FL-20091213-1233-TUR</a>",
      "city": ""
    },
    {
      "occured_at": "<a href='/Akomas/AkomasDetay.aspx?afet=66381'> FL-20091211-1229-TUR</a>",
      "city": "Muğla"
    },
    {
      "occured_at": "<a href='/Akomas/AkomasDetay.aspx?afet=66379'> FL-20091211-1231-TUR</a>",
      "city": "Antalya"
    },
    {
      "occured_at": "<a href='/Akomas/AkomasDetay.aspx?afet=66399'> FL-20091205-1215-TUR</a>",
      "city": "Antalya"
    },
    {
      "occured_at": "<a href='/Akomas/AkomasDetay.aspx?afet=66445'> FL-20091121-1169-TUR</a>",
      "city": "Trabzon"
    },
    {
      "occured_at": "<a href='/Akomas/AkomasDetay.aspx?afet=66448'> FL-20091121-1166-TUR</a>",
      "city": "Giresun"
    },
    {
      "occured_at": "<a href='/Akomas/AkomasDetay.aspx?afet=66502'> FL-20091111-1133-TUR</a>",
      "city": "İzmir"
    },
    {
      "occured_at": "<a href='/Akomas/AkomasDetay.aspx?afet=66501'> FL-20091111-1134-TUR</a>",
      "city": "Muğla"
    },
    {
      "occured_at": "<a href='/Akomas/AkomasDetay.aspx?afet=66530'> FL-20091105-1112-TUR</a>",
      "city": "Osmaniye"
    },
    {
      "occured_at": "<a href='/Akomas/AkomasDetay.aspx?afet=66533'> FL-20091104-1109-TUR</a>",
      "city": "Antalya"
    },
    {
      "occured_at": "<a href='/Akomas/AkomasDetay.aspx?afet=66544'> FL-20091102-1104-TUR</a>",
      "city": "Van"
    },
    {
      "occured_at": "<a href='/Akomas/AkomasDetay.aspx?afet=66552'> FL-20091102-1096-TUR</a>",
      "city": ""
    },
    {
      "occured_at": "<a href='/Akomas/AkomasDetay.aspx?afet=66564'> FL-20091101-1082-TUR</a>",
      "city": "Şanlıurfa"
    },
    {
      "occured_at": "<a href='/Akomas/AkomasDetay.aspx?afet=66565'> FL-20091101-1080-TUR</a>",
      "city": "Siirt"
    },
    {
      "occured_at": "<a href='/Akomas/AkomasDetay.aspx?afet=66569'> FL-20091101-1076-TUR</a>",
      "city": "Adana"
    },
    {
      "occured_at": "<a href='/Akomas/AkomasDetay.aspx?afet=66572'> FL-20091101-1073-TUR</a>",
      "city": "Şırnak"
    },
    {
      "occured_at": "<a href='/Akomas/AkomasDetay.aspx?afet=66582'> FL-20091031-1062-TUR</a>",
      "city": "Elazığ"
    },
    {
      "occured_at": "<a href='/Akomas/AkomasDetay.aspx?afet=66574'> FL-20091031-1071-TUR</a>",
      "city": "Trabzon"
    },
    {
      "occured_at": "<a href='/Akomas/AkomasDetay.aspx?afet=66578'> FL-20091031-1066-TUR</a>",
      "city": "Şanlıurfa"
    },
    {
      "occured_at": "<a href='/Akomas/AkomasDetay.aspx?afet=66573'> FL-20091031-1072-TUR</a>",
      "city": "Denizli"
    },
    {
      "occured_at": "<a href='/Akomas/AkomasDetay.aspx?afet=66577'> FL-20091031-1067-TUR</a>",
      "city": "Kocaeli"
    },
    {
      "occured_at": "<a href='/Akomas/AkomasDetay.aspx?afet=66575'> FL-20091031-1069-TUR</a>",
      "city": "Bingöl"
    },
    {
      "occured_at": "<a href='/Akomas/AkomasDetay.aspx?afet=66576'> FL-20091031-1068-TUR</a>",
      "city": "İstanbul"
    },
    {
      "occured_at": "<a href='/Akomas/AkomasDetay.aspx?afet=66585'> FL-20091030-1059-TUR</a>",
      "city": "Şanlıurfa"
    },
    {
      "occured_at": "<a href='/Akomas/AkomasDetay.aspx?afet=66588'> FL-20091028-1054-TUR</a>",
      "city": "Şanlıurfa"
    },
    {
      "occured_at": "<a href='/Akomas/AkomasDetay.aspx?afet=66703'> FL-20091014-0985-TUR</a>",
      "city": "Antalya"
    },
    {
      "occured_at": "<a href='/Akomas/AkomasDetay.aspx?afet=66704'> FL-20091014-0984-TUR</a>",
      "city": "Antalya"
    },
    {
      "occured_at": "<a href='/Akomas/AkomasDetay.aspx?afet=66739'> FL-20091006-0942-TUR</a>",
      "city": "Rize"
    },
    {
      "occured_at": "<a href='/Akomas/AkomasDetay.aspx?afet=66742'> FL-20091005-0939-TUR</a>",
      "city": "Konya"
    },
    {
      "occured_at": "<a href='/Akomas/AkomasDetay.aspx?afet=66743'> FL-20091005-0938-TUR</a>",
      "city": "Tekirdağ"
    },
    {
      "occured_at": "<a href='/Akomas/AkomasDetay.aspx?afet=66781'> FL-20091004-0917-TUR</a>",
      "city": "Edirne"
    },
    {
      "occured_at": "<a href='/Akomas/AkomasDetay.aspx?afet=66809'> FL-20090927-0886-TUR</a>",
      "city": "Çanakkale"
    },
    {
      "occured_at": "<a href='/Akomas/AkomasDetay.aspx?afet=66815'> FL-20090923-0880-TUR</a>",
      "city": "Artvin"
    },
    {
      "occured_at": "<a href='/Akomas/AkomasDetay.aspx?afet=66818'> FL-20090921-0876-TUR</a>",
      "city": "Adana"
    },
    {
      "occured_at": "<a href='/Akomas/AkomasDetay.aspx?afet=66831'> FL-20090920-0860-TUR</a>",
      "city": "Rize"
    },
    {
      "occured_at": "<a href='/Akomas/AkomasDetay.aspx?afet=66830'> FL-20090920-0861-TUR</a>",
      "city": "Antalya"
    },
    {
      "occured_at": "<a href='/Akomas/AkomasDetay.aspx?afet=66834'> FL-20090916-0857-TUR</a>",
      "city": "Van"
    },
    {
      "occured_at": "<a href='/Akomas/AkomasDetay.aspx?afet=66868'> FL-20090913-0836-TUR</a>",
      "city": "Balıkesir"
    },
    {
      "occured_at": "<a href='/Akomas/AkomasDetay.aspx?afet=66869'> FL-20090913-0835-TUR</a>",
      "city": "Tekirdağ"
    },
    {
      "occured_at": "<a href='/Akomas/AkomasDetay.aspx?afet=66870'> FL-20090913-0834-TUR</a>",
      "city": "Tekirdağ"
    },
    {
      "occured_at": "<a href='/Akomas/AkomasDetay.aspx?afet=66874'> FL-20090912-0830-TUR</a>",
      "city": "Balıkesir"
    },
    {
      "occured_at": "<a href='/Akomas/AkomasDetay.aspx?afet=66872'> FL-20090912-0832-TUR</a>",
      "city": "Edirne"
    },
    {
      "occured_at": "<a href='/Akomas/AkomasDetay.aspx?afet=66876'> FL-20090912-0828-TUR</a>",
      "city": "Aydın"
    },
    {
      "occured_at": "<a href='/Akomas/AkomasDetay.aspx?afet=66877'> FL-20090912-0827-TUR</a>",
      "city": "Çanakkale"
    },
    {
      "occured_at": "<a href='/Akomas/AkomasDetay.aspx?afet=66875'> FL-20090912-0829-TUR</a>",
      "city": "Çanakkale"
    },
    {
      "occured_at": "<a href='/Akomas/AkomasDetay.aspx?afet=66873'> FL-20090912-0831-TUR</a>",
      "city": "İstanbul"
    },
    {
      "occured_at": "<a href='/Akomas/AkomasDetay.aspx?afet=66871'> FL-20090912-0833-TUR</a>",
      "city": "Edirne"
    },
    {
      "occured_at": "<a href='/Akomas/AkomasDetay.aspx?afet=66880'> FL-20090911-0821-TUR</a>",
      "city": "Ağrı"
    },
    {
      "occured_at": "<a href='/Akomas/AkomasDetay.aspx?afet=66883'> FL-20090910-0817-TUR</a>",
      "city": "Yozgat"
    },
    {
      "occured_at": "<a href='/Akomas/AkomasDetay.aspx?afet=66884'> FL-20090909-0816-TUR</a>",
      "city": "Sakarya"
    },
    {
      "occured_at": "<a href='/Akomas/AkomasDetay.aspx?afet=66887'> FL-20090909-0813-TUR</a>",
      "city": "Balıkesir"
    },
    {
      "occured_at": "<a href='/Akomas/AkomasDetay.aspx?afet=66888'> FL-20090909-0812-TUR</a>",
      "city": "Kırıkkale"
    },
    {
      "occured_at": "<a href='/Akomas/AkomasDetay.aspx?afet=66889'> FL-20090909-0811-TUR</a>",
      "city": "Bilecik"
    },
    {
      "occured_at": "<a href='/Akomas/AkomasDetay.aspx?afet=66511'> FL-20090908-0801-TUR</a>",
      "city": "İstanbul"
    },
    {
      "occured_at": "<a href='/Akomas/AkomasDetay.aspx?afet=66510'> FL-20090908-0801-TUR</a>",
      "city": "İstanbul"
    },
    {
      "occured_at": "<a href='/Akomas/AkomasDetay.aspx?afet=66517'> FL-20090908-0801-TUR</a>",
      "city": "İstanbul"
    },
    {
      "occured_at": "<a href='/Akomas/AkomasDetay.aspx?afet=66518'> FL-20090908-0801-TUR</a>",
      "city": "İstanbul"
    },
    {
      "occured_at": "<a href='/Akomas/AkomasDetay.aspx?afet=66516'> FL-20090908-0801-TUR</a>",
      "city": "İstanbul"
    },
    {
      "occured_at": "<a href='/Akomas/AkomasDetay.aspx?afet=66513'> FL-20090908-0801-TUR</a>",
      "city": "İstanbul"
    },
    {
      "occured_at": "<a href='/Akomas/AkomasDetay.aspx?afet=66515'> FL-20090908-0801-TUR</a>",
      "city": "İstanbul"
    },
    {
      "occured_at": "<a href='/Akomas/AkomasDetay.aspx?afet=66512'> FL-20090908-0801-TUR</a>",
      "city": "İstanbul"
    },
    {
      "occured_at": "<a href='/Akomas/AkomasDetay.aspx?afet=66902'> FL-20090908-0801-TUR</a>",
      "city": "İstanbul"
    },
    {
      "occured_at": "<a href='/Akomas/AkomasDetay.aspx?afet=66514'> FL-20090908-0801-TUR</a>",
      "city": "İstanbul"
    },
    {
      "occured_at": "<a href='/Akomas/AkomasDetay.aspx?afet=66900'> FL-20090908-0854-TUR</a>",
      "city": "Tekirdağ"
    },
    {
      "occured_at": "<a href='/Akomas/AkomasDetay.aspx?afet=66901'> FL-20090908-0801-TUR</a>",
      "city": "İstanbul"
    },
    {
      "occured_at": "<a href='/Akomas/AkomasDetay.aspx?afet=66893'> FL-20090908-0806-TUR</a>",
      "city": "Balıkesir"
    },
    {
      "occured_at": "<a href='/Akomas/AkomasDetay.aspx?afet=66896'> FL-20090908-0803-TUR</a>",
      "city": "Kırıkkale"
    },
    {
      "occured_at": "<a href='/Akomas/AkomasDetay.aspx?afet=66894'> FL-20090908-0805-TUR</a>",
      "city": "Çanakkale"
    },
    {
      "occured_at": "<a href='/Akomas/AkomasDetay.aspx?afet=66890'> FL-20090908-0810-TUR</a>",
      "city": "Kütahya"
    },
    {
      "occured_at": "<a href='/Akomas/AkomasDetay.aspx?afet=66891'> FL-20090908-0809-TUR</a>",
      "city": "Burdur"
    },
    {
      "occured_at": "<a href='/Akomas/AkomasDetay.aspx?afet=66895'> FL-20090908-0804-TUR</a>",
      "city": "Balıkesir"
    },
    {
      "occured_at": "<a href='/Akomas/AkomasDetay.aspx?afet=66934'> FL-20090902-0765-TUR</a>",
      "city": "Rize"
    },
    {
      "occured_at": "<a href='/Akomas/AkomasDetay.aspx?afet=67130'> FL-20090730-0524-TUR</a>",
      "city": "Rize"
    },
    {
      "occured_at": "<a href='/Akomas/AkomasDetay.aspx?afet=67135'> FL-20090728-0516-TUR</a>",
      "city": "Düzce"
    },
    {
      "occured_at": "<a href='/Akomas/AkomasDetay.aspx?afet=67138'> FL-20090727-0512-TUR</a>",
      "city": "Rize"
    },
    {
      "occured_at": "<a href='/Akomas/AkomasDetay.aspx?afet=67137'> FL-20090727-0513-TUR</a>",
      "city": "Kastamonu"
    },
    {
      "occured_at": "<a href='/Akomas/AkomasDetay.aspx?afet=67302'> FL-20090722-0482-TUR</a>",
      "city": "Rize"
    },
    {
      "occured_at": "<a href='/Akomas/AkomasDetay.aspx?afet=67303'> FL-20090721-0481-TUR</a>",
      "city": "Giresun"
    },
    {
      "occured_at": "<a href='/Akomas/AkomasDetay.aspx?afet=67325'> FL-20090718-0456-TUR</a>",
      "city": "Kars"
    },
    {
      "occured_at": "<a href='/Akomas/AkomasDetay.aspx?afet=67341'> FL-20090716-0448-TUR</a>",
      "city": "Sinop"
    },
    {
      "occured_at": "<a href='/Akomas/AkomasDetay.aspx?afet=67330'> FL-20090716-0449-TUR</a>",
      "city": "Kastamonu"
    },
    {
      "occured_at": "<a href='/Akomas/AkomasDetay.aspx?afet=67338'> FL-20090715-0438-TUR</a>",
      "city": "Artvin"
    },
    {
      "occured_at": "<a href='/Akomas/AkomasDetay.aspx?afet=67333'> FL-20090715-0445-TUR</a>",
      "city": "Ordu"
    },
    {
      "occured_at": "<a href='/Akomas/AkomasDetay.aspx?afet=67337'> FL-20090715-0439-TUR</a>",
      "city": "Bartın"
    },
    {
      "occured_at": "<a href='/Akomas/AkomasDetay.aspx?afet=67363'> FL-20090710-0414 -TUR</a>",
      "city": "Van"
    },
    {
      "occured_at": "<a href='/Akomas/AkomasDetay.aspx?afet=67406'> FL-20090622-0360-TUR</a>",
      "city": "Ağrı"
    },
    {
      "occured_at": "<a href='/Akomas/AkomasDetay.aspx?afet=67415'> FL-20090620-0347-TUR</a>",
      "city": "Erzurum"
    },
    {
      "occured_at": "<a href='/Akomas/AkomasDetay.aspx?afet=67412'> FL-20090619-0350-TUR</a>",
      "city": "Muş"
    },
    {
      "occured_at": "<a href='/Akomas/AkomasDetay.aspx?afet=67418'> FL-20090619-0344-TUR</a>",
      "city": "Ağrı"
    },
    {
      "occured_at": "<a href='/Akomas/AkomasDetay.aspx?afet=68485'> FL-20090301-0145-TUR</a>",
      "city": "Sakarya"
    },
    {
      "occured_at": "<a href='/Akomas/AkomasDetay.aspx?afet=66216'> FL-20081125-0781-TUR</a>",
      "city": "Mersin"
    },
    {
      "occured_at": "<a href='/Akomas/AkomasDetay.aspx?afet=66217'> FL-20081124-0776-TUR</a>",
      "city": "Adana"
    },
    {
      "occured_at": "<a href='/Akomas/AkomasDetay.aspx?afet=66249'> FL-20081001-0678-TUR</a>",
      "city": "Van"
    },
    {
      "occured_at": "<a href='/Akomas/AkomasDetay.aspx?afet=66126'> FL-20080930-0674-TUR</a>",
      "city": "Kastamonu"
    },
    {
      "occured_at": "<a href='/Akomas/AkomasDetay.aspx?afet=66131'> FL-20080921-0651-TUR</a>",
      "city": "İstanbul"
    },
    {
      "occured_at": "<a href='/Akomas/AkomasDetay.aspx?afet=66132'> FL-20080921-0652-TUR</a>",
      "city": "Antalya"
    },
    {
      "occured_at": "<a href='/Akomas/AkomasDetay.aspx?afet=66134'> FL-20080917-0641-TUR</a>",
      "city": "Bursa"
    },
    {
      "occured_at": "<a href='/Akomas/AkomasDetay.aspx?afet=66029'> FL-20080809-0525-TUR</a>",
      "city": "Van"
    },
    {
      "occured_at": "<a href='/Akomas/AkomasDetay.aspx?afet=66840'> FL-20080722-0454-TUR</a>",
      "city": "Ağrı"
    },
    {
      "occured_at": "<a href='/Akomas/AkomasDetay.aspx?afet=66080'> FL-20080717-0440-TUR</a>",
      "city": "Kars"
    },
    {
      "occured_at": "<a href='/Akomas/AkomasDetay.aspx?afet=66081'> FL-20080715-0432-TUR</a>",
      "city": "Ardahan"
    },
    {
      "occured_at": "<a href='/Akomas/AkomasDetay.aspx?afet=66156'> FL-20080526-0299-TUR</a>",
      "city": "Aksaray"
    },
    {
      "occured_at": "<a href='/Akomas/AkomasDetay.aspx?afet=66157'> FL-20080525-0836-TUR</a>",
      "city": "Manisa"
    },
    {
      "occured_at": "<a href='/Akomas/AkomasDetay.aspx?afet=68393'> FL-20080510-0260-TUR</a>",
      "city": "Adana"
    },
    {
      "occured_at": "<a href='/Akomas/AkomasDetay.aspx?afet=66302'> FL-20080312-0157-TUR</a>",
      "city": "Muğla"
    },
    {
      "occured_at": "<a href='/Akomas/AkomasDetay.aspx?afet=66303'> FL-20080311-0152-TUR</a>",
      "city": "Yozgat"
    },
    {
      "occured_at": "<a href='/Akomas/AkomasDetay.aspx?afet=66304'> FL-20080311-0153-TUR</a>",
      "city": "Bitlis"
    },
    {
      "occured_at": "<a href='/Akomas/AkomasDetay.aspx?afet=67498'> FL-20071214-0594-TUR</a>",
      "city": "Muğla"
    },
    {
      "occured_at": "<a href='/Akomas/AkomasDetay.aspx?afet=67157'> FL-20071120-0562-TUR</a>",
      "city": "Edirne"
    },
    {
      "occured_at": "<a href='/Akomas/AkomasDetay.aspx?afet=67154'> FL-20071119-0565-TUR</a>",
      "city": "İstanbul"
    },
    {
      "occured_at": "<a href='/Akomas/AkomasDetay.aspx?afet=67153'> FL-20071119-0566-TUR</a>",
      "city": "Muğla"
    },
    {
      "occured_at": "<a href='/Akomas/AkomasDetay.aspx?afet=67156'> FL-20071119-0563-TUR</a>",
      "city": "Tekirdağ"
    },
    {
      "occured_at": "<a href='/Akomas/AkomasDetay.aspx?afet=67155'> FL-20071119-0564-TUR</a>",
      "city": "Kırklareli"
    },
    {
      "occured_at": "<a href='/Akomas/AkomasDetay.aspx?afet=67502'> FL-20071116-0556-TUR</a>",
      "city": "Tekirdağ"
    },
    {
      "occured_at": "<a href='/Akomas/AkomasDetay.aspx?afet=67501'> FL-20071116-0556-TUR</a>",
      "city": "Edirne"
    },
    {
      "occured_at": "<a href='/Akomas/AkomasDetay.aspx?afet=67515'> FL-20071014-0497-TUR</a>",
      "city": "İstanbul"
    },
    {
      "occured_at": "<a href='/Akomas/AkomasDetay.aspx?afet=66836'> FL-20071014-0497-TUR</a>",
      "city": "Antalya"
    },
    {
      "occured_at": "<a href='/Akomas/AkomasDetay.aspx?afet=66838'> FL-20071014-0497-TUR</a>",
      "city": "İstanbul"
    },
    {
      "occured_at": "<a href='/Akomas/AkomasDetay.aspx?afet=67522'> FL-20070922-0456-TUR</a>",
      "city": "Düzce"
    },
    {
      "occured_at": "<a href='/Akomas/AkomasDetay.aspx?afet=67177'> FL-20070830-0424-TUR</a>",
      "city": "Ağrı"
    },
    {
      "occured_at": "<a href='/Akomas/AkomasDetay.aspx?afet=67176'> FL-20070829-0425-TUR</a>",
      "city": "Sivas"
    },
    {
      "occured_at": "<a href='/Akomas/AkomasDetay.aspx?afet=67175'> FL-20070829-0426-TUR</a>",
      "city": "Giresun"
    },
    {
      "occured_at": "<a href='/Akomas/AkomasDetay.aspx?afet=67198'> FL-20070824-0413-TUR</a>",
      "city": "Samsun"
    },
    {
      "occured_at": "<a href='/Akomas/AkomasDetay.aspx?afet=67187'> FL-20070809-0386-TUR</a>",
      "city": "Van"
    },
    {
      "occured_at": "<a href='/Akomas/AkomasDetay.aspx?afet=67211'> FL-20070804-0371-TUR</a>",
      "city": "Trabzon"
    },
    {
      "occured_at": "<a href='/Akomas/AkomasDetay.aspx?afet=67210'> FL-20070804-0372-TUR</a>",
      "city": "Erzurum"
    },
    {
      "occured_at": "<a href='/Akomas/AkomasDetay.aspx?afet=67207'> FL-20070802-0375-TUR</a>",
      "city": "Zonguldak"
    },
    {
      "occured_at": "<a href='/Akomas/AkomasDetay.aspx?afet=67250'> FL-20070718-0331-TUR</a>",
      "city": "Muş"
    },
    {
      "occured_at": "<a href='/Akomas/AkomasDetay.aspx?afet=67967'> FL-20070620-0266-TUR</a>",
      "city": "Bitlis"
    },
    {
      "occured_at": "<a href='/Akomas/AkomasDetay.aspx?afet=67970'> FL-20070608-0244-TUR</a>",
      "city": "Kastamonu"
    },
    {
      "occured_at": "<a href='/Akomas/AkomasDetay.aspx?afet=67752'> FL-20070527-0220-TUR</a>",
      "city": "Kayseri"
    },
    {
      "occured_at": "<a href='/Akomas/AkomasDetay.aspx?afet=67757'> FL-20070527-0220-TUR</a>",
      "city": "Ağrı"
    },
    {
      "occured_at": "<a href='/Akomas/AkomasDetay.aspx?afet=67756'> FL-20070527-0220-TUR</a>",
      "city": "Van"
    },
    {
      "occured_at": "<a href='/Akomas/AkomasDetay.aspx?afet=67754'> FL-20070527-0220-TUR</a>",
      "city": "Nevşehir"
    },
    {
      "occured_at": "<a href='/Akomas/AkomasDetay.aspx?afet=67755'> FL-20070527-0220-TUR</a>",
      "city": "Şanlıurfa"
    },
    {
      "occured_at": "<a href='/Akomas/AkomasDetay.aspx?afet=67750'> FL-20070527-0220-TUR</a>",
      "city": "Eskişehir"
    },
    {
      "occured_at": "<a href='/Akomas/AkomasDetay.aspx?afet=67764'> FL-20070518-0209-TUR</a>",
      "city": "Gaziantep"
    },
    {
      "occured_at": "<a href='/Akomas/AkomasDetay.aspx?afet=67765'> FL-20070518-0209-TUR</a>",
      "city": "Şanlıurfa"
    },
    {
      "occured_at": "<a href='/Akomas/AkomasDetay.aspx?afet=67760'> FL-20070514-0213-TUR</a>",
      "city": "Van"
    },
    {
      "occured_at": "<a href='/Akomas/AkomasDetay.aspx?afet=67759'> FL-20070514-0213-TUR</a>",
      "city": "Diyarbakır"
    },
    {
      "occured_at": "<a href='/Akomas/AkomasDetay.aspx?afet=67758'> FL-20070514-0213-TUR</a>",
      "city": "Rize"
    },
    {
      "occured_at": "<a href='/Akomas/AkomasDetay.aspx?afet=67761'> FL-20070514-0213-TUR</a>",
      "city": "Ağrı"
    },
    {
      "occured_at": "<a href='/Akomas/AkomasDetay.aspx?afet=67979'> FL-20070430-0185-TUR</a>",
      "city": "Şırnak"
    },
    {
      "occured_at": "<a href='/Akomas/AkomasDetay.aspx?afet=67984'> FL-20070421-0159-TUR</a>",
      "city": "Muş"
    },
    {
      "occured_at": "<a href='/Akomas/AkomasDetay.aspx?afet=67986'> FL-20070409-0152-TUR</a>",
      "city": "Adana"
    },
    {
      "occured_at": "<a href='/Akomas/AkomasDetay.aspx?afet=78792'> FL-20050604-0153-TUR</a>",
      "city": "Diyarbakır"
    }
  ]
}